odoo10_addon_account_bank_statement_import_coda-10.0.1.0.0.99.dev2-py2.7-nspkg.pth
odoo/addons/account_bank_statement_import_coda/README.rst
odoo/addons/account_bank_statement_import_coda/__init__.py
odoo/addons/account_bank_statement_import_coda/__manifest__.py
odoo/addons/account_bank_statement_import_coda/i18n/account_bank_statement_import_coda.pot
odoo/addons/account_bank_statement_import_coda/i18n/ca_ES.po
odoo/addons/account_bank_statement_import_coda/i18n/de.po
odoo/addons/account_bank_statement_import_coda/i18n/fi.po
odoo/addons/account_bank_statement_import_coda/i18n/fr.po
odoo/addons/account_bank_statement_import_coda/i18n/nl_NL.po
odoo/addons/account_bank_statement_import_coda/static/description/icon.png
odoo/addons/account_bank_statement_import_coda/test_coda_file/Ontvangen_CODA.2012-01-11-18.59.15.txt
odoo/addons/account_bank_statement_import_coda/tests/__init__.py
odoo/addons/account_bank_statement_import_coda/tests/test_import_bank_statement.py
odoo/addons/account_bank_statement_import_coda/wizard/__init__.py
odoo/addons/account_bank_statement_import_coda/wizard/account_bank_statement_import_coda.py
odoo10_addon_account_bank_statement_import_coda-10.0.1.0.0.99.dev2.dist-info/METADATA
odoo10_addon_account_bank_statement_import_coda-10.0.1.0.0.99.dev2.dist-info/RECORD
odoo10_addon_account_bank_statement_import_coda-10.0.1.0.0.99.dev2.dist-info/WHEEL
odoo10_addon_account_bank_statement_import_coda-10.0.1.0.0.99.dev2.dist-info/namespace_packages.txt
odoo10_addon_account_bank_statement_import_coda-10.0.1.0.0.99.dev2.dist-info/top_level.txt
